CHANGELOG.rst
LICENSE
MANIFEST.in
README.rst
pyproject.toml
setup.cfg
setup.py
tox.ini
Mopidy_Playlist.egg-info/PKG-INFO
Mopidy_Playlist.egg-info/SOURCES.txt
Mopidy_Playlist.egg-info/dependency_links.txt
Mopidy_Playlist.egg-info/entry_points.txt
Mopidy_Playlist.egg-info/not-zip-safe
Mopidy_Playlist.egg-info/requires.txt
Mopidy_Playlist.egg-info/top_level.txt
mopidy_playlist/__init__.py
mopidy_playlist/backend.py
mopidy_playlist/ext.conf
tests/__init__.py
tests/test_extension.py