Metadata-Version: 2.1
Name: Mopidy-Playlist
Version: 0.1.0
Summary: Mopidy extension for remote playlist expansion
Home-page: https://github.com/peterlisak/mopidy-playlist
Author: Peter Lisák
Author-email: peter.lisak@gmail.com
License: Apache License, Version 2.0
Platform: UNKNOWN
Classifier: Environment :: No Input/Output (Daemon)
Classifier: Intended Audience :: End Users/Desktop
Classifier: License :: OSI Approved :: Apache Software License
Classifier: Operating System :: OS Independent
Classifier: Programming Language :: Python :: 3
Classifier: Programming Language :: Python :: 3.7
Classifier: Programming Language :: Python :: 3.8
Classifier: Programming Language :: Python :: 3.9
Classifier: Topic :: Multimedia :: Sound/Audio :: Players
Requires-Python: >= 3.7
Provides-Extra: lint
Provides-Extra: test
Provides-Extra: release
Provides-Extra: dev
